odoo/addons/mail_discuss_security/README.rst
odoo/addons/mail_discuss_security/__init__.py
odoo/addons/mail_discuss_security/__manifest__.py
odoo/addons/mail_discuss_security/i18n/fr.po
odoo/addons/mail_discuss_security/i18n/mail_discuss_security.pot
odoo/addons/mail_discuss_security/readme/CONTRIBUTORS.rst
odoo/addons/mail_discuss_security/readme/DESCRIPTION.rst
odoo/addons/mail_discuss_security/security/res_groups.xml
odoo/addons/mail_discuss_security/static/description/icon.png
odoo/addons/mail_discuss_security/static/description/index.html
odoo/addons/mail_discuss_security/static/description/menu_list.png
odoo/addons/mail_discuss_security/static/description/systray.png
odoo/addons/mail_discuss_security/static/src/js/systray_service.esm.js
odoo/addons/mail_discuss_security/views/menu.xml
odoo_addon_mail_discuss_security-16.0.1.0.0.2.dist-info/METADATA
odoo_addon_mail_discuss_security-16.0.1.0.0.2.dist-info/WHEEL
odoo_addon_mail_discuss_security-16.0.1.0.0.2.dist-info/top_level.txt
odoo_addon_mail_discuss_security-16.0.1.0.0.2.dist-info/RECORD
